[
  {
  "a":"Business Processes",
"b":"Product Data Management",
"c":"Product Trigger",
"d":"Non-Order-Specific Trigger",
"e":"Reference Project Search",
"f":"Find Objects in Classes",
"Active":""
},
{
  "a":"Business Processes",
  "b":"Product Data Management",
  "c":"Product Trigger",
  "d":"Non-Order-Specific Trigger",
  "e":"Reference Project Search",
  "f":"Find Objects in Classes",
  "Active":""
},
{
  " a":"Business Processes",
  " b":"Product Data Management",
  " c":"Product Service",
  " d":"Product Structure Management Service",
  " e":"Material/Serial Number Processing",
  " f":"Create Material Serial Number",
  "Active":"Y"
}

]